autoread_dotenv/__init__.py
autoread_dotenv/about.py
autoread_dotenv/py.typed
autoread_dotenv/utils.py
autoread_dotenv-1.0.4.dist-info/WHEEL
autoread_dotenv-1.0.4.dist-info/entry_points.txt
autoread_dotenv-1.0.4.dist-info/METADATA
autoread_dotenv-1.0.4.dist-info/RECORD
