Metadata-Version: 2.3
Name: autoread_dotenv
Version: 1.0.4
Summary: Automatically set env-vars at the beginning of every python-process in your in-project virtualenv.
Keywords: entrypoints,dotenv,sitecustomize
Author: Wouter Vanden Hove
Author-email: Wouter Vanden Hove <wouter@libranet.eu>
License: # MIT License
Classifier: Development Status :: 4 - Beta
Classifier: Environment :: Console
Classifier: Intended Audience :: Developers
Classifier: License :: OSI Approved :: MIT License
Classifier: Operating System :: POSIX :: Linux
Classifier: Operating System :: Microsoft :: Windows
Classifier: Programming Language :: Python :: 3.14
Classifier: Programming Language :: Python :: 3.13
Classifier: Programming Language :: Python :: 3.12
Classifier: Programming Language :: Python :: 3.11
Classifier: Programming Language :: Python :: 3.10
Classifier: Programming Language :: Python :: 3.9
Classifier: Programming Language :: Python :: 3.8
Classifier: Programming Language :: Python :: Implementation :: CPython
Classifier: Programming Language :: Python :: Implementation :: PyPy
Classifier: Typing :: Typed
Requires-Dist: python-dotenv>=1.0.0
Requires-Dist: sitecustomize-entrypoints>=1.1.0
Maintainer: Wouter Vanden Hove
Maintainer-email: Wouter Vanden Hove <wouter@libranet.eu>
Requires-Python: >=3.8
Project-URL: homepage, https://github.com/libranet/autoread-dotenv
Project-URL: repository, https://github.com/libranet/autoread-dotenv
Project-URL: documentation, https://autoread-dotenv.readthedocs.io
